pdfreaderx/__init__.py
pdfreaderx/image_reader.py
pdfreaderx/reader.py
pdfreaderx/table_reader.py
pdfreaderx/text_reader.py
pdfreaderx-0.1.0.dist-info/METADATA
pdfreaderx-0.1.0.dist-info/WHEEL
pdfreaderx-0.1.0.dist-info/top_level.txt
pdfreaderx-0.1.0.dist-info/RECORD
