Metadata-Version: 2.4
Name: pdfreaderx
Version: 0.1.0
Requires-Dist: pdfplumber
Requires-Dist: pytesseract
Requires-Dist: pillow
Requires-Dist: camelot-py[cv]
Requires-Dist: PyMuPDF
Dynamic: requires-dist
